README.rst
setup.cfg
setup.py
features/__init__.py
features/environment.py
features/steps/__init__.py
features/steps/grpc_call_switch.py
features/steps/testsvc/__init__.py
features/steps/testsvc/stdreader.py
features/steps/testsvc/testsvc_pb2.py
features/steps/testsvc/testsvc_pb2_grpc.py
features/steps/testsvc/tstsvc_dynamic_main.py
features/steps/testsvc/tstsvc_main.py
features/support/__init__.py
features/support/model.py
features/support/process_execution.py
oaas_registry/__init__.py
oaas_registry/__main__.py
oaas_registry/oaas_grpc_registry.py
oaas_registry/py.typed
oaas_registry/registry.py
oaas_registry/registry_memory.py
oaas_registry/service_definition.py
oaas_registry.egg-info/PKG-INFO
oaas_registry.egg-info/SOURCES.txt
oaas_registry.egg-info/dependency_links.txt
oaas_registry.egg-info/requires.txt
oaas_registry.egg-info/top_level.txt
test/__init__.py
test/registry_test.py
test/test_serialization.py
test/grpc/__init__.py
test/grpc/test_pb2.py
test/grpc/test_pb2_grpc.py