Metadata-Version: 1.0
Name: oaas-registry
Version: 1.2.0
Summary: oaas_registry
Home-page: UNKNOWN
Author: Bogdan Mustiata
Author-email: bogdan.mustiata@gmail.com
License: BSD
Platform: UNKNOWN
